pseu_cli-1.0.2.data/scripts/pseu
pseucli/__init__.py
pseu_cli-1.0.2.dist-info/LICENSE.txt
pseu_cli-1.0.2.dist-info/METADATA
pseu_cli-1.0.2.dist-info/WHEEL
pseu_cli-1.0.2.dist-info/top_level.txt
pseu_cli-1.0.2.dist-info/RECORD
