Metadata-Version: 2.1
Name: pseu-cli
Version: 1.0.2
Summary: A CLI tool for RNG, shuffling and other pseudorandom stuff.
Home-page: https://github.com/Kevinpgalligan/pseu
Author: Kevin Galligan
Author-email: galligankevinp@gmail.com
License: UNKNOWN
Platform: UNKNOWN
Classifier: Programming Language :: Python :: 3
Classifier: License :: OSI Approved :: MIT License
